filesplit/__init__.py
filesplit/merge.py
filesplit/split.py
filesplit/common/__init__.py
filesplit/common/constant.py
filesplit/common/error.py
filesplit-4.0.0.dist-info/LICENSE.txt
filesplit-4.0.0.dist-info/METADATA
filesplit-4.0.0.dist-info/WHEEL
filesplit-4.0.0.dist-info/top_level.txt
filesplit-4.0.0.dist-info/RECORD
