Metadata-Version: 2.1
Name: filesplit
Version: 4.0.0
Summary: Python module that is capable of splitting files and merging it back.
Home-page: https://github.com/ram-jayapalan/filesplit
Download-URL: https://github.com/ram-jayapalan/filesplit/archive/refs/tags/v4.0.0.tar.gz
Author: Ramprakash Jayapalan
Author-email: ramp16888@gmail.com
License: UNKNOWN
Project-URL: Bug Reports, https://github.com/ram-jayapalan/filesplit/issues
Project-URL: Source, https://github.com/ram-jayapalan/filesplit
Keywords: file split,filesplit,split file,splitfile
Platform: UNKNOWN
Classifier: Intended Audience :: Developers
Classifier: Development Status :: 5 - Production/Stable
Classifier: Operating System :: OS Independent
Classifier: Programming Language :: Python :: 3 :: Only
Classifier: License :: OSI Approved :: MIT License
Requires-Python: >=3, <4
License-File: LICENSE.txt
